popper/__init__.py
popper/archiving.py
popper/cli.py
popper/exceptions.py
popper/utils.py
popper/commands/__init__.py
popper/commands/cmd_add.py
popper/commands/cmd_archive.py
popper/commands/cmd_ci.py
popper/commands/cmd_cleanup.py
popper/commands/cmd_env.py
popper/commands/cmd_info.py
popper/commands/cmd_init.py
popper/commands/cmd_metadata.py
popper/commands/cmd_rm.py
popper/commands/cmd_run.py
popper/commands/cmd_search.py
popper/commands/cmd_stages.py
popper/commands/cmd_version.py
popper/commands/cmd_workflow.py
popper-1.0.0.dist-info/METADATA
popper-1.0.0.dist-info/RECORD
popper-1.0.0.dist-info/WHEEL
popper-1.0.0.dist-info/entry_points.txt
popper-1.0.0.dist-info/top_level.txt
usr/local/etc/bash_completion.d/bash-completion.sh
