Metadata-Version: 2.1
Name: popper
Version: 1.0.0
Summary: Popper CLI tool to generate reproducible papers.
Home-page: http://falsifiable.us
Author: The Popper Development Team
Author-email: ivo@cs.ucsc.edu
License: MIT
Project-URL: Source, https://github.com/systemslab/popper/
Project-URL: Documentation, https://popper.readthedocs.io
Project-URL: Tracker, https://github.com/systemslab/popper/
Project-URL: Say Thanks!, http://gitter.im/falsifiable-us/popper
Keywords: popper reproducibility automation continuous-integration
Platform: UNKNOWN
Requires-Dist: click
Requires-Dist: requests
Requires-Dist: lark-parser
Requires-Dist: pyyaml
Requires-Dist: pyaes
